nswrapslite/__init__.py
nswrapslite/cache.py
nswrapslite/exception.py
nswrapslite/executor.py
nswrapslite/factory.py
nswrapslite/log.py
nswrapslite/retry.py
nswrapslite/singleton.py
nswrapslite/strategy.py
nswrapslite/tenacityretry.py
nswrapslite/timer.py
nswrapslite/utils.py
nswrapslite/validate.py
nswrapslite/wrapped.py
nswrapslite-0.2.0.dist-info/licenses/LICENSE
nswrapslite-0.2.0.dist-info/METADATA
nswrapslite-0.2.0.dist-info/WHEEL
nswrapslite-0.2.0.dist-info/top_level.txt
nswrapslite-0.2.0.dist-info/RECORD
