Metadata-Version: 2.4
Name: nswrapslite
Version: 0.2.0
Summary: 功能强大的Python装饰器工具库，提供各种实用的装饰器和工具函数
Author-email: sandorn <sandorn@live.cn>
License: MIT License
Project-URL: homepage, https://github.com/sandorn/nswraps
Project-URL: repository, https://github.com/sandorn/nswraps
Project-URL: documentation, https://github.com/sandorn/nswraps/wiki
Keywords: python,decorators,tools,utilities,singleton,cache,retry,timer,logging
Classifier: Development Status :: 4 - Beta
Classifier: Intended Audience :: Developers
Classifier: License :: OSI Approved :: MIT License
Classifier: Programming Language :: Python :: 3.13
Classifier: Topic :: Software Development :: Libraries :: Python Modules
Classifier: Topic :: Utilities
Requires-Python: >=3.13
License-File: LICENSE
Requires-Dist: six>=1.16.0
Requires-Dist: websocket-client>=1.5.1
Requires-Dist: xtlog>=0.1.7
Provides-Extra: test
Requires-Dist: pytest>=7.3.0; extra == "test"
Requires-Dist: pytest-asyncio>=0.21.0; extra == "test"
Requires-Dist: pytest-cov>=4.1.0; extra == "test"
Dynamic: license-file
